{"BaseModel.0d86f021-ed9d-4a6a-833a-a4b7c343f429": {"id": "0d86f021-ed9d-4a6a-833a-a4b7c343f429", "created_at": "2023-10-13T11:20:05.565043", "updated_at": "2023-10-14T02:17:28.174517", "name": "My_First_Model", "my_number": 89, "Betty": "56789", "Hassan": "$1000000000", "__class__": "BaseModel"}, "BaseModel.fd329f92-76de-4ca5-b6a8-71b28933cf4c": {"id": "fd329f92-76de-4ca5-b6a8-71b28933cf4c", "created_at": "2023-10-13T11:20:06.739856", "updated_at": "2023-10-13T11:20:06.739935", "name": "My_First_Model", "my_number": 89, "__class__": "BaseModel"}, "BaseModel.2ac8ac95-300f-4aca-8efc-fea77ea31592": {"id": "2ac8ac95-300f-4aca-8efc-fea77ea31592", "created_at": "2023-10-13T11:20:07.745717", "updated_at": "2023-10-13T11:20:07.745853", "name": "My_First_Model", "my_number": 89, "__class__": "BaseModel"}, "BaseModel.d409f098-1b16-4551-be97-8bb47135524f": {"id": "d409f098-1b16-4551-be97-8bb47135524f", "created_at": "2023-10-13T11:20:08.532201", "updated_at": "2023-10-13T11:20:08.532278", "name": "My_First_Model", "my_number": 89, "__class__": "BaseModel"}, "BaseModel.78f4d4b0-1748-4280-a536-40b10e8701e5": {"id": "78f4d4b0-1748-4280-a536-40b10e8701e5", "created_at": "2023-10-13T11:20:10.726757", "updated_at": "2023-10-13T11:20:10.726840", "name": "My_First_Model", "my_number": 89, "__class__": "BaseModel"}, "BaseModel.6433047e-727a-4f2f-85d3-9178a8bd1cba": {"id": "6433047e-727a-4f2f-85d3-9178a8bd1cba", "created_at": "2023-10-13T13:07:50.665761", "updated_at": "2023-10-13T13:07:50.666651", "__class__": "BaseModel"}, "BaseModel.deeb04ed-b2be-46b7-89e5-ebfd91f0ac91": {"id": "deeb04ed-b2be-46b7-89e5-ebfd91f0ac91", "created_at": "2023-10-13T13:34:37.558170", "updated_at": "2023-10-13T13:34:37.558628", "__class__": "BaseModel"}, "BaseModel.91c66d7e-3063-4aa1-99b5-821507bab7fc": {"id": "91c66d7e-3063-4aa1-99b5-821507bab7fc", "created_at": "2023-10-13T13:35:27.571671", "updated_at": "2023-10-13T13:35:27.571711", "__class__": "BaseModel"}, "BaseModel.f29a948d-e6be-4583-99c0-14001c988edb": {"id": "f29a948d-e6be-4583-99c0-14001c988edb", "created_at": "2023-10-13T13:36:49.625762", "updated_at": "2023-10-13T13:36:49.625880", "__class__": "BaseModel"}}
